cppbktree.cpython-39-x86_64-linux-gnu.so
cppbktree-0.1.0.dist-info/top_level.txt
cppbktree-0.1.0.dist-info/LICENSE
cppbktree-0.1.0.dist-info/RECORD
cppbktree-0.1.0.dist-info/WHEEL
cppbktree-0.1.0.dist-info/METADATA
